mads_datasets/__init__.py
mads_datasets/base.py
mads_datasets/datatools.py
mads_datasets/settings.py
mads_datasets/datasets/__init__.py
mads_datasets/datasets/basicdatasets.py
mads_datasets/datasets/torchdatasets.py
mads_datasets/factories/__init__.py
mads_datasets/factories/basicfactories.py
mads_datasets/factories/torchfactories.py
mads_datasets-0.3.14.dist-info/METADATA
mads_datasets-0.3.14.dist-info/WHEEL
mads_datasets-0.3.14.dist-info/RECORD
