Metadata-Version: 2.3
Name: mads-datasets
Version: 0.3.14
Summary: Datasets for the master applied data science
Project-URL: GitHub, https://github.com/raoulg/mads_datasets
Author-email: Raoul Grouls <Raoul.Grouls@han.nl>
License: MIT
Requires-Python: >=3.11
Requires-Dist: keyring>=24.2.0
Requires-Dist: loguru>=0.7.2
Requires-Dist: numpy>=1.24.4
Requires-Dist: pandas>=2.0.3
Requires-Dist: pillow>=9.5.0
Requires-Dist: polars>=1.5.0
Requires-Dist: pydantic>=1.10.8
Requires-Dist: requests>=2.0.0
Requires-Dist: tqdm>=4.0.0
Provides-Extra: torch
Requires-Dist: torch>=2.0.1; extra == 'torch'
